pysen_ls/__init__.py
pysen_ls/__main__.py
pysen_ls/config.py
pysen_ls/diagnostic.py
pysen_ls/logger.py
pysen_ls/py.typed
pysen_ls/runtime.py
pysen_ls/server.py
pysen_ls/types.py
pysen_ls/workspace.py
pysen_ls-0.1.2.dist-info/LICENSE
pysen_ls-0.1.2.dist-info/METADATA
pysen_ls-0.1.2.dist-info/WHEEL
pysen_ls-0.1.2.dist-info/entry_points.txt
pysen_ls-0.1.2.dist-info/top_level.txt
pysen_ls-0.1.2.dist-info/RECORD
